setup.cfg
setup.py
cor/__init__.py
cor/api.py
cor/comm.py
cor/utils.py
cor.egg-info/PKG-INFO
cor.egg-info/SOURCES.txt
cor.egg-info/dependency_links.txt
cor.egg-info/requires.txt
cor.egg-info/top_level.txt
cor/protocol/__init__.py
cor/protocol/lifecycle.proto
cor/protocol/lifecycle_pb2.py
cor/protocol/log.proto
cor/protocol/log_pb2.py
cor/protocol/message.proto
cor/protocol/message_pb2.py