Metadata-Version: 1.1
Name: cor
Version: 5.0
Summary: Distributed modular computing framework that runs anywhere
Home-page: https://github.com/bahusvel/COR-Framework-Python
Author: Denis Lavrov
Author-email: bahus.vel@gmail.com
License: UNKNOWN
Keywords: distributed,modular,microservices
Platform: UNKNOWN
Provides: cor
